README
setup.py
shoutcast_search/__init__.py
shoutcast_search/shoutcast_search.py
shoutcast_search.egg-info/PKG-INFO
shoutcast_search.egg-info/SOURCES.txt
shoutcast_search.egg-info/dependency_links.txt
shoutcast_search.egg-info/top_level.txt