Metadata-Version: 1.0
Name: shoutcast-search
Version: 0.3.1
Summary: Search shoutcast.com web radio stations
Home-page: http://code.k2h.se
Author: Henrik Hallberg
Author-email: halhen@k2h.se
License: GPL
Platform: UNKNOWN
Classifier: Intended Audience :: Developers
Classifier: License :: OSI Approved :: GNU General Public License (GPL)
Classifier: Programming Language :: Python
